dkdc_env/__init__.py
dkdc_env/main.py
dkdc_env-0.0.1.dist-info/METADATA
dkdc_env-0.0.1.dist-info/WHEEL
dkdc_env-0.0.1.dist-info/top_level.txt
dkdc_env-0.0.1.dist-info/RECORD
